pygame_chart/__init__.py
pygame_chart/pygame_chart.py
pygame_chart/settings.py
pygame_chart/util_functions.py
pygame_chart-1.0.0.dist-info/LICENSE
pygame_chart-1.0.0.dist-info/METADATA
pygame_chart-1.0.0.dist-info/WHEEL
pygame_chart-1.0.0.dist-info/top_level.txt
pygame_chart-1.0.0.dist-info/RECORD
