Metadata-Version: 2.1
Name: pygame_chart
Version: 1.0.0
Summary: A package for drawing charts in pygame apps
Author-email: Enes Safak <safakenes@gmail.com>
Project-URL: Homepage, https://github.com/enessafak/pygame-chart
Classifier: Programming Language :: Python :: 3
Classifier: License :: OSI Approved :: MIT License
Classifier: Operating System :: OS Independent
Requires-Python: >=3.9.10
License-File: LICENSE
